ucdp/__init__.py
ucdp/data.py
ucdp/event.py
ucdp/ucdp.py
micro_chrome_devtools_protocol-0.2.1.dist-info/LICENSE
micro_chrome_devtools_protocol-0.2.1.dist-info/METADATA
micro_chrome_devtools_protocol-0.2.1.dist-info/WHEEL
micro_chrome_devtools_protocol-0.2.1.dist-info/top_level.txt
micro_chrome_devtools_protocol-0.2.1.dist-info/RECORD
