Metadata-Version: 2.1
Name: micro-chrome-devtools-protocol
Version: 0.2.1
Summary: A lightweight library for speaking the Chrome DevTools Protocol in order to debug JavaScript
Home-page: https://github.com/aib/ucdp
Author: Orhan "aib" Kavrakoglu
Author-email: aibok42@gmail.com
License: MIT
Keywords: chrome,chromium,devtools,protocol,node,nodejs,electron,debugging,debugger
Classifier: Intended Audience :: Developers
Classifier: Topic :: Software Development :: Debuggers
Classifier: Programming Language :: Python :: 3
Classifier: Programming Language :: JavaScript
Classifier: License :: OSI Approved :: MIT License
Classifier: Operating System :: OS Independent
Requires-Python: >=3.8
License-File: LICENSE
